rga_stat/__init__.py
rga_stat/rga_hypothesis.py
rga_stat-1.1.2.dist-info/LICENSE
rga_stat-1.1.2.dist-info/METADATA
rga_stat-1.1.2.dist-info/WHEEL
rga_stat-1.1.2.dist-info/top_level.txt
rga_stat-1.1.2.dist-info/RECORD
